pbgca/__init__.py
pbgca/cluster.py
pbgca/clusterer.py
pbgca/connectivity_matrix.py
pbgca/cube_generator.py
pbgca/plot_generator.py
pbgca-0.1.1.dist-info/LICENSE
pbgca-0.1.1.dist-info/METADATA
pbgca-0.1.1.dist-info/WHEEL
pbgca-0.1.1.dist-info/top_level.txt
pbgca-0.1.1.dist-info/RECORD
