Metadata-Version: 2.1
Name: pbgca
Version: 0.1.1
Summary: Physically based galaxy clustering algorithm
Home-page: https://github.com/jeromeshan/pbgca
Author: Andrey Shan
Author-email: avshan@edu.hse.ru
License: MIT
Platform: UNKNOWN
Classifier: Intended Audience :: Developers
Classifier: License :: OSI Approved :: MIT License
Classifier: Programming Language :: Python
Classifier: Programming Language :: Python :: 3
Classifier: Programming Language :: Python :: 3.6
Classifier: Programming Language :: Python :: 3.7
Classifier: Programming Language :: Python :: 3.8
Classifier: Programming Language :: Python :: 3.9
Classifier: Operating System :: OS Independent
License-File: LICENSE
Requires-Dist: numpy
Requires-Dist: pandas
Requires-Dist: ray
Requires-Dist: scipy
Requires-Dist: plotly
Requires-Dist: sklearn
